ventral_api_client/__init__.py
ventral_api_client/client.py
ventral_api_client/config.py
ventral_api_client-0.1.0.dist-info/LICENSE
ventral_api_client-0.1.0.dist-info/METADATA
ventral_api_client-0.1.0.dist-info/WHEEL
ventral_api_client-0.1.0.dist-info/top_level.txt
ventral_api_client-0.1.0.dist-info/RECORD
