Metadata-Version: 2.2
Name: ventral-api-client
Version: 0.1.0
Summary: A client for Ventral Vision AI's API
Home-page: https://github.com/kontaktdoo/ventral
Author: Bare Luka Zagar
Author-email: bare@ventral.ai
Classifier: Programming Language :: Python :: 3
Classifier: License :: OSI Approved :: Apache Software License
Classifier: Operating System :: OS Independent
Requires-Python: >=3.7
License-File: LICENSE
Dynamic: author
Dynamic: author-email
Dynamic: classifier
Dynamic: description
Dynamic: description-content-type
Dynamic: home-page
Dynamic: requires-python
Dynamic: summary
